{
  "envVars": [
    {"name": "RUNNER_WORKSPACE", "value": "./publish-symbols-test/src"},
    {"name": "GITHUB_REPOSITORY", "value": "publish-symbols"},
    {"name": "GITHUB_WORKFLOW", "value": "1"},
    {"name": "GITHUB_RUN_NUMBER", "value": "1"},
    {"name": "GITHUB_RUN_ID", "value": "1"}
  ],
  "inputs": [
    {"name": "accountName", "value": "1es-cat"},
    {"name": "symbolServiceUrl", "value": "https://artifacts.dev.azure.com"},
    {"name": "personalAccessToken", "value": ""},
    {"name": "searchPattern", "value": "**/bin/**/*.pdb"}
  ]
}
